rus2num/__init__.py
rus2num/main.py
rus2num/number.py
rus2num-0.1.0.dist-info/LICENSE
rus2num-0.1.0.dist-info/METADATA
rus2num-0.1.0.dist-info/WHEEL
rus2num-0.1.0.dist-info/RECORD
