Metadata-Version: 2.1
Name: rus2num
Version: 0.1.0
Summary: (Russian) numerals to numbers transform
Home-page: https://github.com/saarus72/rus2num
License: MIT
Author: Alexander Stupnikov
Author-email: saarus72@gmail.com
Requires-Python: >=3.8,<4.0
Classifier: License :: OSI Approved :: MIT License
Classifier: Programming Language :: Python :: 3
Classifier: Programming Language :: Python :: 3.8
Classifier: Programming Language :: Python :: 3.9
Classifier: Programming Language :: Python :: 3.10
Classifier: Programming Language :: Python :: 3.11
Classifier: Programming Language :: Python :: 3.12
Requires-Dist: natasha (==0.10.0)
Requires-Dist: yargy (==0.12.0)
Project-URL: Repository, https://github.com/saarus72/rus2num
